sluggard/__init__.py
sluggard/sluggard.py
sluggard-1.0.0.dist-info/LICENSE
sluggard-1.0.0.dist-info/METADATA
sluggard-1.0.0.dist-info/WHEEL
sluggard-1.0.0.dist-info/entry_points.txt
sluggard-1.0.0.dist-info/top_level.txt
sluggard-1.0.0.dist-info/RECORD
