Metadata-Version: 2.1
Name: sluggard
Version: 1.0.0
Summary: directory packaging tool
Home-page: https://github.com/SiLeader/sluggard
Author: SiLeader and Cerussite
Author-email: UNKNOWN
License: UNKNOWN
Keywords: packaging,compression,archiving
Platform: UNKNOWN
Classifier: Environment :: Console
Classifier: License :: OSI Approved
Classifier: License :: OSI Approved :: GNU General Public License v3 (GPLv3)
Classifier: Topic :: System :: Archiving
Classifier: Topic :: System :: Archiving :: Compression
Classifier: Topic :: System :: Archiving :: Packaging
